{
  "date": "2026-03-15",
  "generated_at": "2026-03-15T13:54:59.356308",
  "data": {
    "date": "2026-03-15",
    "mundial_2026_start": "2026-06-11",
    "days_remaining": 88,
    "events": [],
    "news": [
      {
        "title": "Liga Profesional de Fútbol",
        "description": "",
        "url": "https://www.tycsports.com/liga-profesional-de-futbol.html",
        "source": "TyC Sports",
        "published_at": "2026-03-15T13:55:00.768548"
      },
      {
        "title": "Con gol de Messi, Inter Miami le ganó a Independiente del Valle",
        "description": "",
        "url": "https://www.tycsports.com/futbol/amistosos-clubes-2026-inter-miami-vs-independiente-del-valle-amistosos-messi-gol-penal-de-paul-suarez-id712654.html",
        "source": "TyC Sports",
        "published_at": "2026-03-15T13:55:00.768735"
      }
    ]
  },
  "message": "**Buenos días 🇦🇷**\n\nFaltan 88 días para el Mundial 2026 ⚽\n\n📊 Dato del día: Lionel Messi ha jugado en tres países diferentes en el año 2026. El capitán de la Scaloneta sigue siendo la referencia mundial del fútbol y prepara su sexta participación en un Mundial 🏆\n\n**Noticia del día:**\nCon gol de Messi, Inter Miami le ganó a Independiente del Valle (TyC Sports).\n\nCoronados de gloria vivamos 🩵🤍🩵",
  "status": "published",
  "updated_at": "2026-03-15T13:55:07.693160",
  "published_at": "2026-03-15T13:55:08.372249",
  "pre_approved": true,
  "pre_approved_at": "2026-03-15T13:55:07.693170"
}