{
  "date": "2026-07-03",
  "generated_at": "2026-03-25T12:17:53.764290",
  "data": {
    "date": "2026-07-03",
    "mundial_2026_start": "2026-06-11",
    "mundial_2026_end": "2026-07-19",
    "days_remaining": -22,
    "mundial_phase": "durante_mundial",
    "mundial_day": 23,
    "events": [
      {
        "date": "1990-07-03",
        "type": "world_cup",
        "priority": "high",
        "person": "Goycochea",
        "description": "Argentina elimina a Italia por penales y pasa a la final."
      },
      {
        "date": "2010-07-03",
        "type": "world_cup",
        "priority": "high",
        "person": "Maradona",
        "description": "Dura eliminación de Sudáfrica 2010 tras caer 4-0 con Alemania."
      },
      {
        "date": "1994-07-03",
        "type": "world_cup",
        "priority": "medium",
        "person": "N/A",
        "description": "Eliminación de USA 94 tras perder 3-2 con Rumania."
      },
      {
        "date": "2021-07-03",
        "type": "match",
        "priority": "medium",
        "person": "Lionel Messi",
        "description": "Goleada 3-0 a Ecuador con un Messi estelar."
      },
      {
        "date": "2026-07-03",
        "type": "match",
        "priority": "medium",
        "person": "N/A",
        "description": "Mundial 2026 - Día de descanso antes de octavos de final."
      }
    ],
    "news": []
  },
  "message": "Buenos días 🇦🇷\n\nFaltan 23 días para el Mundial 2026 ⚽\n\nHoy Argentina elimina a Italia por penales y pasa a la final. Un día como hoy en 1990, la Scaloneta también alcanzó la final del Mundial 🏆\n\nCoronados de gloria vivamos 🩵🤍🩵",
  "status": "draft",
  "updated_at": null,
  "published_at": null,
  "pre_approved": false,
  "pre_approved_at": null
}