{
  "date": "2026-03-18",
  "generated_at": "2026-03-18T14:41:13.394311",
  "data": {
    "date": "2026-03-18",
    "mundial_2026_start": "2026-06-11",
    "days_remaining": 85,
    "events": [],
    "news": [
      {
        "title": "Liga Profesional de Fútbol",
        "description": "",
        "url": "https://www.tycsports.com/liga-profesional-de-futbol.html",
        "source": "TyC Sports",
        "published_at": "2026-03-18T14:41:15.081583"
      },
      {
        "title": "Con gol de Messi, Inter Miami le ganó a Independiente del Valle",
        "description": "",
        "url": "https://www.tycsports.com/futbol/amistosos-clubes-2026-inter-miami-vs-independiente-del-valle-amistosos-messi-gol-penal-de-paul-suarez-id712654.html",
        "source": "TyC Sports",
        "published_at": "2026-03-18T14:41:15.081820"
      }
    ]
  },
  "message": "**Buenos días 🇦🇷**\n\nFaltan 85 días para el Mundial 2026 ⚽\n\nCon gol de Messi, Inter Miami le ganó a Independiente del Valle (TyC Sports) 📊. Este resultado refleja la calidad y el espíritu competitivo de la Scaloneta.\n\n📊 Dato del día: Lionel Messi es el jugador con más títulos oficiales en la historia del fútbol 🔥\n\nCoronados de gloria vivamos 🩵🤍🩵",
  "status": "published",
  "updated_at": "2026-03-18T14:41:23.503372",
  "published_at": "2026-03-18T14:41:24.241193",
  "pre_approved": true,
  "pre_approved_at": "2026-03-18T14:41:23.503382"
}