{
  "type": "image",
  "source": "AFA / Getty Images",
  "description": "Selección Argentina — Bolivia 6-1 Argentina en La Paz: la peor derrota de Argentina en Eliminatorias. Papelón histórico ba",
  "credits": "AFA / Getty Images",
  "event_date": "2009-04-01",
  "tags": [
    "seleccion",
    "failure",
    "argentina"
  ],
  "search_suggestion": "seleccion argentina failure site:afa.com.ar OR gettyimages.com",
  "notes": "Contexto: Bolivia 6-1 Argentina en La Paz: la peor derrota de Argentina en Eliminatorias. ",
  "reference_date": "2026-04-01",
  "event_type": "failure",
  "event_priority": "high",
  "event_description": "Bolivia 6-1 Argentina en La Paz: la peor derrota de Argentina en Eliminatorias. Papelón histórico bajo la dirección de Maradona."
}