{
  "type": "image",
  "source": "Getty Images / EFE / Archivo deportivo",
  "description": "Foto de Matteo Guendouzi con la camiseta de la Selección Argentina (27 años en 2026)",
  "credits": "Getty Images Sport",
  "event_date": "1999-04-14",
  "tags": [
    "matteo_guendouzi",
    "cumpleanos",
    "seleccion"
  ],
  "search_suggestion": "\"Matteo Guendouzi\" seleccion argentina site:gettyimages.com OR site:efe.com",
  "notes": "Preferir foto con la albiceleste en partido oficial",
  "reference_date": "2026-04-14",
  "event_type": "birthday",
  "event_priority": "low",
  "event_description": "Cumpleaños de Matteo Guendouzi. Mediocampista francés, subcampeón del mundo en Qatar 2022 ante Argentina."
}